sphinx_susiai_theme/__init__.py
sphinx_susiai_theme/layout.html
sphinx_susiai_theme/search.html
sphinx_susiai_theme/theme.conf
sphinx_susiai_theme/static/susi-logo-footer.svg
sphinx_susiai_theme/static/susi-logo.png
sphinx_susiai_theme/static/susi.css_t
sphinx_susiai_theme-0.0.1.dist-info/DESCRIPTION.rst
sphinx_susiai_theme-0.0.1.dist-info/METADATA
sphinx_susiai_theme-0.0.1.dist-info/RECORD
sphinx_susiai_theme-0.0.1.dist-info/WHEEL
sphinx_susiai_theme-0.0.1.dist-info/entry_points.txt
sphinx_susiai_theme-0.0.1.dist-info/metadata.json
sphinx_susiai_theme-0.0.1.dist-info/top_level.txt
