Metadata-Version: 2.0
Name: sphinx-susiai-theme
Version: 0.0.1
Summary: A Sphinx theme specific to SUSI AI's Projects
Home-page: https://github.com/fossasia/sphinx_susiai_theme
Author: Balaji R
Author-email: rbalajis25@gmail.com
License: GNU
Platform: any
Classifier: Framework :: Sphinx :: Extension
Classifier: Framework :: Sphinx :: Theme
Classifier: Intended Audience :: Developers
Classifier: Operating System :: OS Independent
Classifier: Topic :: Documentation :: Sphinx
Classifier: Topic :: Software Development :: Documentation
Requires-Dist: sphinx (>=1.3)
